src/models.py
src/server.py
mcp_sys_bridge-0.1.5.dist-info/METADATA
mcp_sys_bridge-0.1.5.dist-info/WHEEL
mcp_sys_bridge-0.1.5.dist-info/entry_points.txt
mcp_sys_bridge-0.1.5.dist-info/licenses/license
mcp_sys_bridge-0.1.5.dist-info/RECORD
